[{"@id":"_:genid1","@type":["http://www.w3.org/2002/07/owl#Restriction"],"http://www.w3.org/2002/07/owl#allValuesFrom":[{"@id":"http://ontology.eil.utoronto.ca/icontact.owl#StreetDirection"}],"http://www.w3.org/2002/07/owl#onProperty":[{"@id":"http://ontology.eil.utoronto.ca/icontact.owl#hasStreetDirection"}]},{"@id":"_:genid10","@type":["http://www.w3.org/2002/07/owl#Restriction"],"http://www.w3.org/2002/07/owl#allValuesFrom":[{"@id":"http://www.w3.org/2001/XMLSchema#string"}],"http://www.w3.org/2002/07/owl#onProperty":[{"@id":"http://ontology.eil.utoronto.ca/icontact.owl#hasStreet"}]},{"@id":"_:genid11","@type":["http://www.w3.org/2002/07/owl#Restriction"],"http://www.w3.org/2002/07/owl#allValuesFrom":[{"@id":"http://www.w3.org/2001/XMLSchema#nonNegativeInteger"}],"http://www.w3.org/2002/07/owl#onProperty":[{"@id":"http://ontology.eil.utoronto.ca/icontact.owl#hasUnitNumber"}]},{"@id":"_:genid12","@type":["http://www.w3.org/2002/07/owl#Restriction"],"http://www.w3.org/2002/07/owl#onDataRange":[{"@id":"http://www.w3.org/2001/XMLSchema#nonNegativeInteger"}],"http://www.w3.org/2002/07/owl#onProperty":[{"@id":"http://ontology.eil.utoronto.ca/icontact.owl#hasStreetNumber"}],"http://www.w3.org/2002/07/owl#qualifiedCardinality":[{"@type":"http://www.w3.org/2001/XMLSchema#nonNegativeInteger","@value":"1"}]},{"@id":"_:genid13","@type":["http://www.w3.org/2002/07/owl#Restriction"],"http://www.w3.org/2002/07/owl#onDataRange":[{"@id":"http://www.w3.org/2001/XMLSchema#string"}],"http://www.w3.org/2002/07/owl#onProperty":[{"@id":"http://www.w3.org/2003/01/geo/wgs84_pos#lat"}],"http://www.w3.org/2002/07/owl#qualifiedCardinality":[{"@type":"http://www.w3.org/2001/XMLSchema#nonNegativeInteger","@value":"1"}]},{"@id":"_:genid14","@type":["http://www.w3.org/2002/07/owl#Restriction"],"http://www.w3.org/2002/07/owl#onDataRange":[{"@id":"http://www.w3.org/2001/XMLSchema#string"}],"http://www.w3.org/2002/07/owl#onProperty":[{"@id":"http://www.w3.org/2003/01/geo/wgs84_pos#long"}],"http://www.w3.org/2002/07/owl#qualifiedCardinality":[{"@type":"http://www.w3.org/2001/XMLSchema#nonNegativeInteger","@value":"1"}]},{"@id":"_:genid15","@type":["http://www.w3.org/2002/07/owl#Class"],"http://www.w3.org/2002/07/owl#oneOf":[{"@list":[{"@id":"http://ontology.eil.utoronto.ca/icontact.owl#Cottage"},{"@id":"http://ontology.eil.utoronto.ca/icontact.owl#Home"},{"@id":"http://ontology.eil.utoronto.ca/icontact.owl#Work"}]}]},{"@id":"_:genid19","@type":["http://www.w3.org/2002/07/owl#Restriction"],"http://www.w3.org/2002/07/owl#hasValue":[{"@id":"http://ontology.eil.utoronto.ca/icontact.owl#CellPhone"}],"http://www.w3.org/2002/07/owl#onProperty":[{"@id":"http://ontology.eil.utoronto.ca/icontact.owl#hasPhoneType"}]},{"@id":"_:genid2","@type":["http://www.w3.org/2002/07/owl#Restriction"],"http://www.w3.org/2002/07/owl#allValuesFrom":[{"@id":"http://ontology.eil.utoronto.ca/icontact.owl#StreetType"}],"http://www.w3.org/2002/07/owl#onProperty":[{"@id":"http://ontology.eil.utoronto.ca/icontact.owl#hasStreetType"}]},{"@id":"_:genid20","@type":["http://www.w3.org/2002/07/owl#Restriction"],"http://www.w3.org/2002/07/owl#hasValue":[{"@id":"http://ontology.eil.utoronto.ca/icontact.owl#Cottage"}],"http://www.w3.org/2002/07/owl#onProperty":[{"@id":"http://ontology.eil.utoronto.ca/icontact.owl#hasAddressType"}]},{"@id":"_:genid21","@type":["http://www.w3.org/2002/07/owl#Restriction"],"http://www.w3.org/2002/07/owl#hasValue":[{"@id":"http://ontology.eil.utoronto.ca/icontact.owl#FaxPhone"}],"http://www.w3.org/2002/07/owl#onProperty":[{"@id":"http://ontology.eil.utoronto.ca/icontact.owl#hasPhoneType"}]},{"@id":"_:genid22","@type":["http://www.w3.org/2002/07/owl#Restriction"],"http://www.w3.org/2002/07/owl#hasValue":[{"@id":"http://ontology.eil.utoronto.ca/icontact.owl#Home"}],"http://www.w3.org/2002/07/owl#onProperty":[{"@id":"http://ontology.eil.utoronto.ca/icontact.owl#hasAddressType"}]},{"@id":"_:genid23","@type":["http://www.w3.org/2002/07/owl#Restriction"],"http://www.w3.org/2002/07/owl#hasValue":[{"@id":"http://ontology.eil.utoronto.ca/icontact.owl#HomePhone"}],"http://www.w3.org/2002/07/owl#onProperty":[{"@id":"http://ontology.eil.utoronto.ca/icontact.owl#hasPhoneType"}]},{"@id":"_:genid24","@type":["http://www.w3.org/2002/07/owl#Restriction"],"http://www.w3.org/2002/07/owl#onProperty":[{"@id":"http://ontology.eil.utoronto.ca/icontact.owl#dayofWeek"}],"http://www.w3.org/2002/07/owl#someValuesFrom":[{"@id":"http://ontology.eil.utoronto.ca/icontact.owl#DaysOfWeek"}]},{"@id":"_:genid25","@type":["http://www.w3.org/2002/07/owl#Restriction"],"http://www.w3.org/2002/07/owl#onDataRange":[{"@id":"http://www.w3.org/2001/XMLSchema#dateTime"}],"http://www.w3.org/2002/07/owl#onProperty":[{"@id":"http://ontology.eil.utoronto.ca/icontact.owl#hasClosingTime"}],"http://www.w3.org/2002/07/owl#qualifiedCardinality":[{"@type":"http://www.w3.org/2001/XMLSchema#nonNegativeInteger","@value":"1"}]},{"@id":"_:genid26","@type":["http://www.w3.org/2002/07/owl#Restriction"],"http://www.w3.org/2002/07/owl#onDataRange":[{"@id":"http://www.w3.org/2001/XMLSchema#dateTime"}],"http://www.w3.org/2002/07/owl#onProperty":[{"@id":"http://ontology.eil.utoronto.ca/icontact.owl#hasOpeningTime"}],"http://www.w3.org/2002/07/owl#qualifiedCardinality":[{"@type":"http://www.w3.org/2001/XMLSchema#nonNegativeInteger","@value":"1"}]},{"@id":"_:genid27","@type":["http://www.w3.org/2002/07/owl#Restriction"],"http://www.w3.org/2002/07/owl#onClass":[{"@id":"http://ontology.eil.utoronto.ca/icontact.owl#PhoneType"}],"http://www.w3.org/2002/07/owl#onProperty":[{"@id":"http://ontology.eil.utoronto.ca/icontact.owl#hasPhoneType"}],"http://www.w3.org/2002/07/owl#qualifiedCardinality":[{"@type":"http://www.w3.org/2001/XMLSchema#nonNegativeInteger","@value":"1"}]},{"@id":"_:genid28","@type":["http://www.w3.org/2002/07/owl#Restriction"],"http://www.w3.org/2002/07/owl#onDataRange":[{"@id":"http://www.w3.org/2001/XMLSchema#nonNegativeInteger"}],"http://www.w3.org/2002/07/owl#onProperty":[{"@id":"http://ontology.eil.utoronto.ca/icontact.owl#hasAreaCode"}],"http://www.w3.org/2002/07/owl#qualifiedCardinality":[{"@type":"http://www.w3.org/2001/XMLSchema#nonNegativeInteger","@value":"1"}]},{"@id":"_:genid29","@type":["http://www.w3.org/2002/07/owl#Restriction"],"http://www.w3.org/2002/07/owl#onDataRange":[{"@id":"http://www.w3.org/2001/XMLSchema#nonNegativeInteger"}],"http://www.w3.org/2002/07/owl#onProperty":[{"@id":"http://ontology.eil.utoronto.ca/icontact.owl#hasCountryCode"}],"http://www.w3.org/2002/07/owl#qualifiedCardinality":[{"@type":"http://www.w3.org/2001/XMLSchema#nonNegativeInteger","@value":"1"}]},{"@id":"_:genid3","@type":["http://www.w3.org/2002/07/owl#Restriction"],"http://www.w3.org/2002/07/owl#onClass":[{"@id":"http://schema.org/City"}],"http://www.w3.org/2002/07/owl#onProperty":[{"@id":"http://ontology.eil.utoronto.ca/icontact.owl#hasCity"}],"http://www.w3.org/2002/07/owl#qualifiedCardinality":[{"@type":"http://www.w3.org/2001/XMLSchema#nonNegativeInteger","@value":"1"}]},{"@id":"_:genid30","@type":["http://www.w3.org/2002/07/owl#Restriction"],"http://www.w3.org/2002/07/owl#onDataRange":[{"@id":"http://www.w3.org/2001/XMLSchema#nonNegativeInteger"}],"http://www.w3.org/2002/07/owl#onProperty":[{"@id":"http://ontology.eil.utoronto.ca/icontact.owl#hasPhoneNumber"}],"http://www.w3.org/2002/07/owl#qualifiedCardinality":[{"@type":"http://www.w3.org/2001/XMLSchema#nonNegativeInteger","@value":"1"}]},{"@id":"_:genid31","@type":["http://www.w3.org/2002/07/owl#Class"],"http://www.w3.org/2002/07/owl#oneOf":[{"@list":[{"@id":"http://ontology.eil.utoronto.ca/icontact.owl#CellPhone"},{"@id":"http://ontology.eil.utoronto.ca/icontact.owl#FaxPhone"},{"@id":"http://ontology.eil.utoronto.ca/icontact.owl#HomePhone"},{"@id":"http://ontology.eil.utoronto.ca/icontact.owl#TollFreePhone"},{"@id":"http://ontology.eil.utoronto.ca/icontact.owl#WorkPhone"}]}]},{"@id":"_:genid37","@type":["http://www.w3.org/2002/07/owl#Class"],"http://www.w3.org/2002/07/owl#oneOf":[{"@list":[{"@id":"http://ontology.eil.utoronto.ca/icontact.owl#East"},{"@id":"http://ontology.eil.utoronto.ca/icontact.owl#North"},{"@id":"http://ontology.eil.utoronto.ca/icontact.owl#South"},{"@id":"http://ontology.eil.utoronto.ca/icontact.owl#West"}]}]},{"@id":"_:genid4","@type":["http://www.w3.org/2002/07/owl#Restriction"],"http://www.w3.org/2002/07/owl#onClass":[{"@id":"http://schema.org/Country"}],"http://www.w3.org/2002/07/owl#onProperty":[{"@id":"http://ontology.eil.utoronto.ca/icontact.owl#hasCountry"}],"http://www.w3.org/2002/07/owl#qualifiedCardinality":[{"@type":"http://www.w3.org/2001/XMLSchema#nonNegativeInteger","@value":"1"}]},{"@id":"_:genid42","@type":["http://www.w3.org/2002/07/owl#Class"],"http://www.w3.org/2002/07/owl#oneOf":[{"@list":[{"@id":"http://ontology.eil.utoronto.ca/icontact.owl#Avenue"},{"@id":"http://ontology.eil.utoronto.ca/icontact.owl#Boulevard"},{"@id":"http://ontology.eil.utoronto.ca/icontact.owl#Circle"},{"@id":"http://ontology.eil.utoronto.ca/icontact.owl#Crescent"},{"@id":"http://ontology.eil.utoronto.ca/icontact.owl#Drive"},{"@id":"http://ontology.eil.utoronto.ca/icontact.owl#Road"},{"@id":"http://ontology.eil.utoronto.ca/icontact.owl#Street"}]}]},{"@id":"_:genid5","@type":["http://www.w3.org/2002/07/owl#Restriction"],"http://www.w3.org/2002/07/owl#onClass":[{"@id":"http://schema.org/State"}],"http://www.w3.org/2002/07/owl#onProperty":[{"@id":"http://ontology.eil.utoronto.ca/icontact.owl#hasState"}],"http://www.w3.org/2002/07/owl#qualifiedCardinality":[{"@type":"http://www.w3.org/2001/XMLSchema#nonNegativeInteger","@value":"1"}]},{"@id":"_:genid50","@type":["http://www.w3.org/2002/07/owl#Restriction"],"http://www.w3.org/2002/07/owl#hasValue":[{"@id":"http://ontology.eil.utoronto.ca/icontact.owl#TollFreePhone"}],"http://www.w3.org/2002/07/owl#onProperty":[{"@id":"http://ontology.eil.utoronto.ca/icontact.owl#hasPhoneType"}]},{"@id":"_:genid51","@type":["http://www.w3.org/2002/07/owl#Restriction"],"http://www.w3.org/2002/07/owl#hasValue":[{"@id":"http://ontology.eil.utoronto.ca/icontact.owl#Work"}],"http://www.w3.org/2002/07/owl#onProperty":[{"@id":"http://ontology.eil.utoronto.ca/icontact.owl#hasAddressType"}]},{"@id":"_:genid52","@type":["http://www.w3.org/2002/07/owl#Restriction"],"http://www.w3.org/2002/07/owl#hasValue":[{"@id":"http://ontology.eil.utoronto.ca/icontact.owl#WorkPhone"}],"http://www.w3.org/2002/07/owl#onProperty":[{"@id":"http://ontology.eil.utoronto.ca/icontact.owl#hasPhoneType"}]},{"@id":"_:genid53","@type":["http://www.w3.org/2002/07/owl#AllDisjointClasses"],"http://www.w3.org/2002/07/owl#members":[{"@list":[{"@id":"http://ontology.eil.utoronto.ca/icontact.owl#Address"},{"@id":"http://ontology.eil.utoronto.ca/icontact.owl#AddressType"},{"@id":"http://ontology.eil.utoronto.ca/icontact.owl#DaysOfWeek"},{"@id":"http://ontology.eil.utoronto.ca/icontact.owl#HoursOfOperation"},{"@id":"http://ontology.eil.utoronto.ca/icontact.owl#PhoneNumber"},{"@id":"http://ontology.eil.utoronto.ca/icontact.owl#PhoneType"},{"@id":"http://ontology.eil.utoronto.ca/icontact.owl#StreetDirection"},{"@id":"http://ontology.eil.utoronto.ca/icontact.owl#StreetType"}]}]},{"@id":"_:genid6","@type":["http://www.w3.org/2002/07/owl#Restriction"],"http://www.w3.org/2002/07/owl#onClass":[{"@id":"http://www.opengis.net/ont/geosparql#Feature"}],"http://www.w3.org/2002/07/owl#onProperty":[{"@id":"https://w3id.org/icity/SpatialLoc/hasLocation"}],"http://www.w3.org/2002/07/owl#qualifiedCardinality":[{"@type":"http://www.w3.org/2001/XMLSchema#nonNegativeInteger","@value":"1"}]},{"@id":"_:genid7","@type":["http://www.w3.org/2002/07/owl#Restriction"],"http://www.w3.org/2002/07/owl#allValuesFrom":[{"@id":"http://www.w3.org/2001/XMLSchema#string"}],"http://www.w3.org/2002/07/owl#onProperty":[{"@id":"http://ontology.eil.utoronto.ca/icontact.owl#hasBuilding"}]},{"@id":"_:genid8","@type":["http://www.w3.org/2002/07/owl#Restriction"],"http://www.w3.org/2002/07/owl#allValuesFrom":[{"@id":"http://www.w3.org/2001/XMLSchema#string"}],"http://www.w3.org/2002/07/owl#onProperty":[{"@id":"http://ontology.eil.utoronto.ca/icontact.owl#hasCitySection"}]},{"@id":"_:genid9","@type":["http://www.w3.org/2002/07/owl#Restriction"],"http://www.w3.org/2002/07/owl#allValuesFrom":[{"@id":"http://www.w3.org/2001/XMLSchema#string"}],"http://www.w3.org/2002/07/owl#onProperty":[{"@id":"http://ontology.eil.utoronto.ca/icontact.owl#hasPostalCode"}]},{"@id":"http://creativecommons.org/ns#license","@type":["http://www.w3.org/2002/07/owl#AnnotationProperty"]},{"@id":"http://ontology.eil.utoronto.ca/icontact.owl#Address","@type":["http://www.w3.org/2002/07/owl#Class"],"http://purl.org/dc/terms/description":[{"@language":"en","@value":"Address is the main concept for a contact.  It has been designed to represent any type of address in the world, including India and the UK.  For example, the property hasBuilding is important in many UK and Indian addresses to further identify the person or business location.\n\nStreet information is divided into separate properties to fully indentify direction (hasStreetDirection), Type (hasStreetType), etc.  See the associated list of properties for more."}],"http://www.w3.org/2000/01/rdf-schema#label":[{"@language":"en","@value":"Address"}],"http://www.w3.org/2000/01/rdf-schema#subClassOf":[{"@id":"http://ontology.eil.utoronto.ca/icontact.owl#iContactThing"},{"@id":"_:genid1"},{"@id":"_:genid2"},{"@id":"_:genid3"},{"@id":"_:genid4"},{"@id":"_:genid5"},{"@id":"_:genid6"},{"@id":"_:genid7"},{"@id":"_:genid8"},{"@id":"_:genid9"},{"@id":"_:genid10"},{"@id":"_:genid11"},{"@id":"_:genid12"},{"@id":"_:genid13"},{"@id":"_:genid14"}]},{"@id":"http://ontology.eil.utoronto.ca/icontact.owl#AddressType","@type":["http://www.w3.org/2002/07/owl#Class"],"http://purl.org/dc/terms/description":[{"@language":"en","@value":"Different type for home, office, cottage, etc."}],"http://www.w3.org/2000/01/rdf-schema#label":[{"@language":"en","@value":"Address Type"}],"http://www.w3.org/2000/01/rdf-schema#subClassOf":[{"@id":"http://ontology.eil.utoronto.ca/icontact.owl#iContactThing"}],"http://www.w3.org/2002/07/owl#equivalentClass":[{"@id":"_:genid15"}]},{"@id":"http://ontology.eil.utoronto.ca/icontact.owl#Avenue","@type":["http://www.w3.org/2002/07/owl#NamedIndividual"],"http://www.w3.org/2000/01/rdf-schema#label":[{"@language":"en","@value":"Avenue"}]},{"@id":"http://ontology.eil.utoronto.ca/icontact.owl#Boulevard","@type":["http://www.w3.org/2002/07/owl#NamedIndividual"],"http://www.w3.org/2000/01/rdf-schema#label":[{"@language":"en","@value":"Boulevard"}]},{"@id":"http://ontology.eil.utoronto.ca/icontact.owl#CellNumber","@type":["http://www.w3.org/2002/07/owl#Class"],"http://www.w3.org/2000/01/rdf-schema#label":[{"@language":"en","@value":"Mobile Telephone Number"}],"http://www.w3.org/2000/01/rdf-schema#subClassOf":[{"@id":"http://ontology.eil.utoronto.ca/icontact.owl#PhoneNumber"},{"@id":"_:genid19"}]},{"@id":"http://ontology.eil.utoronto.ca/icontact.owl#CellPhone","@type":["http://www.w3.org/2002/07/owl#NamedIndividual"],"http://www.w3.org/2000/01/rdf-schema#label":[{"@language":"en","@value":"Cell Phone"}]},{"@id":"http://ontology.eil.utoronto.ca/icontact.owl#Circle","@type":["http://www.w3.org/2002/07/owl#NamedIndividual"],"http://www.w3.org/2000/01/rdf-schema#label":[{"@language":"en","@value":"Circle"}]},{"@id":"http://ontology.eil.utoronto.ca/icontact.owl#Cottage","@type":["http://www.w3.org/2002/07/owl#NamedIndividual"],"http://www.w3.org/2000/01/rdf-schema#label":[{"@language":"en","@value":"Cottage Address"}]},{"@id":"http://ontology.eil.utoronto.ca/icontact.owl#CottageAddress","@type":["http://www.w3.org/2002/07/owl#Class"],"http://www.w3.org/2000/01/rdf-schema#label":[{"@language":"en","@value":"Cottage Address"}],"http://www.w3.org/2000/01/rdf-schema#subClassOf":[{"@id":"http://ontology.eil.utoronto.ca/icontact.owl#Address"},{"@id":"_:genid20"}]},{"@id":"http://ontology.eil.utoronto.ca/icontact.owl#Crescent","@type":["http://www.w3.org/2002/07/owl#NamedIndividual"],"http://www.w3.org/2000/01/rdf-schema#label":[{"@language":"en","@value":"Crescent"}]},{"@id":"http://ontology.eil.utoronto.ca/icontact.owl#DaysOfWeek","@type":["http://www.w3.org/2002/07/owl#Class"],"http://www.w3.org/2000/01/rdf-schema#label":[{"@language":"en","@value":"Days of the Week"}],"http://www.w3.org/2000/01/rdf-schema#subClassOf":[{"@id":"http://ontology.eil.utoronto.ca/icontact.owl#iContactThing"}]},{"@id":"http://ontology.eil.utoronto.ca/icontact.owl#Drive","@type":["http://www.w3.org/2002/07/owl#NamedIndividual"],"http://www.w3.org/2000/01/rdf-schema#label":[{"@language":"en","@value":"Drive"}]},{"@id":"http://ontology.eil.utoronto.ca/icontact.owl#East","@type":["http://www.w3.org/2002/07/owl#NamedIndividual"],"http://www.w3.org/2000/01/rdf-schema#label":[{"@language":"en","@value":"East"}]},{"@id":"http://ontology.eil.utoronto.ca/icontact.owl#FaxNumber","@type":["http://www.w3.org/2002/07/owl#Class"],"http://www.w3.org/2000/01/rdf-schema#label":[{"@language":"en","@value":"Fax Telephone Number"}],"http://www.w3.org/2000/01/rdf-schema#subClassOf":[{"@id":"http://ontology.eil.utoronto.ca/icontact.owl#PhoneNumber"},{"@id":"_:genid21"}]},{"@id":"http://ontology.eil.utoronto.ca/icontact.owl#FaxPhone","@type":["http://www.w3.org/2002/07/owl#NamedIndividual"],"http://www.w3.org/2000/01/rdf-schema#label":[{"@language":"en","@value":"Fax Line"}]},{"@id":"http://ontology.eil.utoronto.ca/icontact.owl#Friday","@type":["http://www.w3.org/2002/07/owl#NamedIndividual","http://ontology.eil.utoronto.ca/icontact.owl#DaysOfWeek"],"http://www.w3.org/2000/01/rdf-schema#label":[{"@language":"en","@value":"Friday"}]},{"@id":"http://ontology.eil.utoronto.ca/icontact.owl#Home","@type":["http://www.w3.org/2002/07/owl#NamedIndividual"],"http://www.w3.org/2000/01/rdf-schema#label":[{"@language":"en","@value":"Home Address"}]},{"@id":"http://ontology.eil.utoronto.ca/icontact.owl#HomeAddress","@type":["http://www.w3.org/2002/07/owl#Class"],"http://www.w3.org/2000/01/rdf-schema#label":[{"@language":"en","@value":"Home Address"}],"http://www.w3.org/2000/01/rdf-schema#subClassOf":[{"@id":"http://ontology.eil.utoronto.ca/icontact.owl#Address"},{"@id":"_:genid22"}]},{"@id":"http://ontology.eil.utoronto.ca/icontact.owl#HomeNumber","@type":["http://www.w3.org/2002/07/owl#Class"],"http://www.w3.org/2000/01/rdf-schema#label":[{"@language":"en","@value":"Home Telephone Number"}],"http://www.w3.org/2000/01/rdf-schema#subClassOf":[{"@id":"http://ontology.eil.utoronto.ca/icontact.owl#PhoneNumber"},{"@id":"_:genid23"}]},{"@id":"http://ontology.eil.utoronto.ca/icontact.owl#HomePhone","@type":["http://www.w3.org/2002/07/owl#NamedIndividual"],"http://www.w3.org/2000/01/rdf-schema#label":[{"@language":"en","@value":"Home Phone"}]},{"@id":"http://ontology.eil.utoronto.ca/icontact.owl#HoursOfOperation","@type":["http://www.w3.org/2002/07/owl#Class"],"http://purl.org/dc/terms/description":[{"@language":"en","@value":"HoursOfOperation class provides the ability to define when the contact \"opens\" and \"closes\". Used for businesses."}],"http://www.w3.org/2000/01/rdf-schema#subClassOf":[{"@id":"http://ontology.eil.utoronto.ca/icontact.owl#iContactThing"},{"@id":"_:genid24"},{"@id":"_:genid25"},{"@id":"_:genid26"}]},{"@id":"http://ontology.eil.utoronto.ca/icontact.owl#Monday","@type":["http://www.w3.org/2002/07/owl#NamedIndividual","http://ontology.eil.utoronto.ca/icontact.owl#DaysOfWeek"],"http://www.w3.org/2000/01/rdf-schema#label":[{"@language":"en","@value":"Monday"}]},{"@id":"http://ontology.eil.utoronto.ca/icontact.owl#North","@type":["http://www.w3.org/2002/07/owl#NamedIndividual"],"http://www.w3.org/2000/01/rdf-schema#label":[{"@language":"en","@value":"North"}]},{"@id":"http://ontology.eil.utoronto.ca/icontact.owl#OperatingProperty","@type":["http://www.w3.org/2002/07/owl#ObjectProperty"],"http://purl.org/dc/terms/description":[{"@language":"en","@value":"Properties that define the hours of operation of the contact."}],"http://www.w3.org/2000/01/rdf-schema#subPropertyOf":[{"@id":"http://ontology.eil.utoronto.ca/icontact.owl#contactProperty"}]},{"@id":"http://ontology.eil.utoronto.ca/icontact.owl#PhoneNumber","@type":["http://www.w3.org/2002/07/owl#Class"],"http://purl.org/dc/terms/description":[{"@language":"en","@value":"PhoneNumber is another core class. It is divided into country code, and phone number."}],"http://www.w3.org/2000/01/rdf-schema#label":[{"@language":"en","@value":"Phone Number"}],"http://www.w3.org/2000/01/rdf-schema#subClassOf":[{"@id":"http://ontology.eil.utoronto.ca/icontact.owl#iContactThing"},{"@id":"_:genid27"},{"@id":"_:genid28"},{"@id":"_:genid29"},{"@id":"_:genid30"}]},{"@id":"http://ontology.eil.utoronto.ca/icontact.owl#PhoneType","@type":["http://www.w3.org/2002/07/owl#Class"],"http://purl.org/dc/terms/description":[{"@language":"en","@value":"Types of phoned include home, cell, work, etc."}],"http://www.w3.org/2000/01/rdf-schema#label":[{"@language":"en","@value":"Phone Type"}],"http://www.w3.org/2000/01/rdf-schema#subClassOf":[{"@id":"http://ontology.eil.utoronto.ca/icontact.owl#iContactThing"}],"http://www.w3.org/2002/07/owl#equivalentClass":[{"@id":"_:genid31"}]},{"@id":"http://ontology.eil.utoronto.ca/icontact.owl#Road","@type":["http://www.w3.org/2002/07/owl#NamedIndividual"],"http://www.w3.org/2000/01/rdf-schema#label":[{"@language":"en","@value":"Road"}]},{"@id":"http://ontology.eil.utoronto.ca/icontact.owl#Saturday","@type":["http://www.w3.org/2002/07/owl#NamedIndividual","http://ontology.eil.utoronto.ca/icontact.owl#DaysOfWeek"],"http://www.w3.org/2000/01/rdf-schema#label":[{"@language":"en","@value":"Saturday"}]},{"@id":"http://ontology.eil.utoronto.ca/icontact.owl#SchemaOrgThing","@type":["http://www.w3.org/2002/07/owl#Class"]},{"@id":"http://ontology.eil.utoronto.ca/icontact.owl#South","@type":["http://www.w3.org/2002/07/owl#NamedIndividual"],"http://www.w3.org/2000/01/rdf-schema#label":[{"@language":"en","@value":"South"}]},{"@id":"http://ontology.eil.utoronto.ca/icontact.owl#Street","@type":["http://www.w3.org/2002/07/owl#NamedIndividual"],"http://www.w3.org/2000/01/rdf-schema#label":[{"@language":"en","@value":"Street"}]},{"@id":"http://ontology.eil.utoronto.ca/icontact.owl#StreetDirection","@type":["http://www.w3.org/2002/07/owl#Class"],"http://www.w3.org/2000/01/rdf-schema#label":[{"@language":"en","@value":"Street Direction"}],"http://www.w3.org/2000/01/rdf-schema#subClassOf":[{"@id":"http://ontology.eil.utoronto.ca/icontact.owl#iContactThing"}],"http://www.w3.org/2002/07/owl#equivalentClass":[{"@id":"_:genid37"}]},{"@id":"http://ontology.eil.utoronto.ca/icontact.owl#StreetType","@type":["http://www.w3.org/2002/07/owl#Class"],"http://www.w3.org/2000/01/rdf-schema#label":[{"@language":"en","@value":"Street Type"}],"http://www.w3.org/2000/01/rdf-schema#subClassOf":[{"@id":"http://ontology.eil.utoronto.ca/icontact.owl#iContactThing"}],"http://www.w3.org/2002/07/owl#equivalentClass":[{"@id":"_:genid42"}]},{"@id":"http://ontology.eil.utoronto.ca/icontact.owl#Sunday","@type":["http://www.w3.org/2002/07/owl#NamedIndividual","http://ontology.eil.utoronto.ca/icontact.owl#DaysOfWeek"],"http://www.w3.org/2000/01/rdf-schema#label":[{"@language":"en","@value":"Sunday"}]},{"@id":"http://ontology.eil.utoronto.ca/icontact.owl#Thursday","@type":["http://www.w3.org/2002/07/owl#NamedIndividual","http://ontology.eil.utoronto.ca/icontact.owl#DaysOfWeek"],"http://www.w3.org/2000/01/rdf-schema#label":[{"@language":"en","@value":"Thursday"}]},{"@id":"http://ontology.eil.utoronto.ca/icontact.owl#TollFreeNumber","@type":["http://www.w3.org/2002/07/owl#Class"],"http://www.w3.org/2000/01/rdf-schema#label":[{"@language":"en","@value":"Toll  Free Telephone Number"}],"http://www.w3.org/2000/01/rdf-schema#subClassOf":[{"@id":"http://ontology.eil.utoronto.ca/icontact.owl#PhoneNumber"},{"@id":"_:genid50"}]},{"@id":"http://ontology.eil.utoronto.ca/icontact.owl#TollFreePhone","@type":["http://www.w3.org/2002/07/owl#NamedIndividual"],"http://www.w3.org/2000/01/rdf-schema#label":[{"@language":"en","@value":"Toll Free Number"}]},{"@id":"http://ontology.eil.utoronto.ca/icontact.owl#Tuesday","@type":["http://www.w3.org/2002/07/owl#NamedIndividual","http://ontology.eil.utoronto.ca/icontact.owl#DaysOfWeek"],"http://www.w3.org/2000/01/rdf-schema#label":[{"@language":"en","@value":"Tuesday"}]},{"@id":"http://ontology.eil.utoronto.ca/icontact.owl#Wednesday","@type":["http://www.w3.org/2002/07/owl#NamedIndividual","http://ontology.eil.utoronto.ca/icontact.owl#DaysOfWeek"],"http://www.w3.org/2000/01/rdf-schema#label":[{"@language":"en","@value":"Wednesday"}]},{"@id":"http://ontology.eil.utoronto.ca/icontact.owl#West","@type":["http://www.w3.org/2002/07/owl#NamedIndividual"],"http://www.w3.org/2000/01/rdf-schema#label":[{"@language":"en","@value":"West"}]},{"@id":"http://ontology.eil.utoronto.ca/icontact.owl#Work","@type":["http://www.w3.org/2002/07/owl#NamedIndividual"],"http://www.w3.org/2000/01/rdf-schema#label":[{"@language":"en","@value":"WorkAddress"}]},{"@id":"http://ontology.eil.utoronto.ca/icontact.owl#WorkAddress","@type":["http://www.w3.org/2002/07/owl#Class"],"http://www.w3.org/2000/01/rdf-schema#label":[{"@language":"en","@value":"Work Address"}],"http://www.w3.org/2000/01/rdf-schema#subClassOf":[{"@id":"http://ontology.eil.utoronto.ca/icontact.owl#Address"},{"@id":"_:genid51"}]},{"@id":"http://ontology.eil.utoronto.ca/icontact.owl#WorkNumber","@type":["http://www.w3.org/2002/07/owl#Class"],"http://www.w3.org/2000/01/rdf-schema#label":[{"@language":"en","@value":"Work Telephone Number"}],"http://www.w3.org/2000/01/rdf-schema#subClassOf":[{"@id":"http://ontology.eil.utoronto.ca/icontact.owl#PhoneNumber"},{"@id":"_:genid52"}]},{"@id":"http://ontology.eil.utoronto.ca/icontact.owl#WorkPhone","@type":["http://www.w3.org/2002/07/owl#NamedIndividual"],"http://www.w3.org/2000/01/rdf-schema#label":[{"@language":"en","@value":"Work Phone"}]},{"@id":"http://ontology.eil.utoronto.ca/icontact.owl#addressDataProperty","@type":["http://www.w3.org/2002/07/owl#DatatypeProperty"],"http://www.w3.org/2000/01/rdf-schema#subPropertyOf":[{"@id":"http://ontology.eil.utoronto.ca/icontact.owl#hasContactDataProperty"}]},{"@id":"http://ontology.eil.utoronto.ca/icontact.owl#addressProperty","@type":["http://www.w3.org/2002/07/owl#ObjectProperty"],"http://www.w3.org/2000/01/rdf-schema#domain":[{"@id":"http://ontology.eil.utoronto.ca/icontact.owl#Address"}],"http://www.w3.org/2000/01/rdf-schema#subPropertyOf":[{"@id":"http://ontology.eil.utoronto.ca/icontact.owl#contactProperty"}]},{"@id":"http://ontology.eil.utoronto.ca/icontact.owl#contactProperty","@type":["http://www.w3.org/2002/07/owl#ObjectProperty"]},{"@id":"http://ontology.eil.utoronto.ca/icontact.owl#dayofWeek","@type":["http://www.w3.org/2002/07/owl#ObjectProperty"],"http://www.w3.org/2000/01/rdf-schema#comment":[{"@language":"en","@value":"Specifies the day of the week, e.g., Monday, that the times apply to.  This is the default for that day and can be overidden by the \"hasDate\" property."}],"http://www.w3.org/2000/01/rdf-schema#range":[{"@id":"http://ontology.eil.utoronto.ca/icontact.owl#DaysOfWeek"}],"http://www.w3.org/2000/01/rdf-schema#subPropertyOf":[{"@id":"http://ontology.eil.utoronto.ca/icontact.owl#OperatingProperty"}]},{"@id":"http://ontology.eil.utoronto.ca/icontact.owl#emailDataProperty","@type":["http://www.w3.org/2002/07/owl#DatatypeProperty"],"http://www.w3.org/2000/01/rdf-schema#subPropertyOf":[{"@id":"http://ontology.eil.utoronto.ca/icontact.owl#hasContactDataProperty"}]},{"@id":"http://ontology.eil.utoronto.ca/icontact.owl#hasAddress","@type":["http://www.w3.org/2002/07/owl#ObjectProperty"],"http://www.w3.org/2000/01/rdf-schema#comment":[{"@language":"en","@value":"hasAddress links any class to the Address class."}],"http://www.w3.org/2000/01/rdf-schema#range":[{"@id":"http://ontology.eil.utoronto.ca/icontact.owl#Address"}],"http://www.w3.org/2000/01/rdf-schema#subPropertyOf":[{"@id":"http://ontology.eil.utoronto.ca/icontact.owl#contactProperty"}]},{"@id":"http://ontology.eil.utoronto.ca/icontact.owl#hasAddressType","@type":["http://www.w3.org/2002/07/owl#ObjectProperty"],"http://www.w3.org/2000/01/rdf-schema#label":[{"@language":"en","@value":"has Address Type"}],"http://www.w3.org/2000/01/rdf-schema#range":[{"@id":"http://ontology.eil.utoronto.ca/icontact.owl#AddressType"}],"http://www.w3.org/2000/01/rdf-schema#subPropertyOf":[{"@id":"http://ontology.eil.utoronto.ca/icontact.owl#addressProperty"}]},{"@id":"http://ontology.eil.utoronto.ca/icontact.owl#hasAreaCode","@type":["http://www.w3.org/2002/07/owl#DatatypeProperty"],"http://www.w3.org/2000/01/rdf-schema#label":[{"@language":"en","@value":"has Area Code"}],"http://www.w3.org/2000/01/rdf-schema#subPropertyOf":[{"@id":"http://ontology.eil.utoronto.ca/icontact.owl#telephoneDataProperty"}]},{"@id":"http://ontology.eil.utoronto.ca/icontact.owl#hasBuilding","@type":["http://www.w3.org/2002/07/owl#DatatypeProperty"],"http://purl.org/dc/terms/description":[{"@language":"en","@value":"The building where the address is located.  Often used in countries like England, India and Japan."}],"http://www.w3.org/2000/01/rdf-schema#label":[{"@language":"en","@value":"has Building"}],"http://www.w3.org/2000/01/rdf-schema#subPropertyOf":[{"@id":"http://ontology.eil.utoronto.ca/icontact.owl#addressDataProperty"}]},{"@id":"http://ontology.eil.utoronto.ca/icontact.owl#hasCity","@type":["http://www.w3.org/2002/07/owl#ObjectProperty"],"http://purl.org/dc/terms/description":[{"@language":"en","@value":"has City"}],"http://www.w3.org/2000/01/rdf-schema#subPropertyOf":[{"@id":"http://ontology.eil.utoronto.ca/icontact.owl#addressProperty"}]},{"@id":"http://ontology.eil.utoronto.ca/icontact.owl#hasCitySection","@type":["http://www.w3.org/2002/07/owl#DatatypeProperty"],"http://purl.org/dc/terms/description":[{"@language":"en","@value":"The section of the city where the address is located.  Often used in countries like England, India and Japan."}],"http://www.w3.org/2000/01/rdf-schema#label":[{"@language":"en","@value":"has City Section"}],"http://www.w3.org/2000/01/rdf-schema#subPropertyOf":[{"@id":"http://ontology.eil.utoronto.ca/icontact.owl#addressDataProperty"}]},{"@id":"http://ontology.eil.utoronto.ca/icontact.owl#hasClosingTime","@type":["http://www.w3.org/2002/07/owl#DatatypeProperty"],"http://www.w3.org/2000/01/rdf-schema#label":[{"@language":"en","@value":"has Closing Time"}],"http://www.w3.org/2000/01/rdf-schema#range":[{"@id":"http://www.w3.org/2001/XMLSchema#dateTime"}],"http://www.w3.org/2000/01/rdf-schema#subPropertyOf":[{"@id":"http://ontology.eil.utoronto.ca/icontact.owl#operatingDataProperty"}]},{"@id":"http://ontology.eil.utoronto.ca/icontact.owl#hasContactDataProperty","@type":["http://www.w3.org/2002/07/owl#DatatypeProperty"]},{"@id":"http://ontology.eil.utoronto.ca/icontact.owl#hasCountry","@type":["http://www.w3.org/2002/07/owl#ObjectProperty"],"http://www.w3.org/2000/01/rdf-schema#label":[{"@language":"en","@value":"has Country"}],"http://www.w3.org/2000/01/rdf-schema#subPropertyOf":[{"@id":"http://ontology.eil.utoronto.ca/icontact.owl#addressProperty"}]},{"@id":"http://ontology.eil.utoronto.ca/icontact.owl#hasCountryCode","@type":["http://www.w3.org/2002/07/owl#DatatypeProperty"],"http://www.w3.org/2000/01/rdf-schema#label":[{"@language":"en","@value":"has Country Code"}],"http://www.w3.org/2000/01/rdf-schema#subPropertyOf":[{"@id":"http://ontology.eil.utoronto.ca/icontact.owl#telephoneDataProperty"}]},{"@id":"http://ontology.eil.utoronto.ca/icontact.owl#hasDate","@type":["http://www.w3.org/2002/07/owl#DatatypeProperty"],"http://purl.org/dc/terms/description":[{"@language":"en","@value":"Specifies the opening and closing times for a specific date.  For example, used to provide times for a holiday which deviates from the norm."}],"http://www.w3.org/2000/01/rdf-schema#label":[{"@language":"en","@value":"has Date"}],"http://www.w3.org/2000/01/rdf-schema#range":[{"@id":"http://www.w3.org/2001/XMLSchema#dateTime"}],"http://www.w3.org/2000/01/rdf-schema#subPropertyOf":[{"@id":"http://ontology.eil.utoronto.ca/icontact.owl#operatingDataProperty"}]},{"@id":"http://ontology.eil.utoronto.ca/icontact.owl#hasEmail","@type":["http://www.w3.org/2002/07/owl#ObjectProperty"],"http://www.w3.org/2000/01/rdf-schema#label":[{"@language":"en","@value":"has Email"}],"http://www.w3.org/2000/01/rdf-schema#subPropertyOf":[{"@id":"http://ontology.eil.utoronto.ca/icontact.owl#contactProperty"}]},{"@id":"http://ontology.eil.utoronto.ca/icontact.owl#hasGeoCoordinates","@type":["http://www.w3.org/2002/07/owl#ObjectProperty"],"http://www.w3.org/2000/01/rdf-schema#label":[{"@language":"en","@value":"has Geo Coordinates"}],"http://www.w3.org/2000/01/rdf-schema#subPropertyOf":[{"@id":"http://ontology.eil.utoronto.ca/icontact.owl#addressProperty"}]},{"@id":"http://ontology.eil.utoronto.ca/icontact.owl#hasLocation","@type":["http://www.w3.org/2002/07/owl#DatatypeProperty"],"http://purl.org/dc/terms/description":[{"@language":"en","@value":"Closet street intersection for the organization."}],"http://www.w3.org/2000/01/rdf-schema#label":[{"@language":"en","@value":"has Location"}],"http://www.w3.org/2000/01/rdf-schema#range":[{"@id":"http://www.w3.org/2001/XMLSchema#string"}],"http://www.w3.org/2000/01/rdf-schema#subPropertyOf":[{"@id":"http://ontology.eil.utoronto.ca/icontact.owl#hasContactDataProperty"}]},{"@id":"http://ontology.eil.utoronto.ca/icontact.owl#hasOpeningTime","@type":["http://www.w3.org/2002/07/owl#DatatypeProperty"],"http://www.w3.org/2000/01/rdf-schema#label":[{"@language":"en","@value":"has Opening Time"}],"http://www.w3.org/2000/01/rdf-schema#range":[{"@id":"http://www.w3.org/2001/XMLSchema#dateTime"}],"http://www.w3.org/2000/01/rdf-schema#subPropertyOf":[{"@id":"http://ontology.eil.utoronto.ca/icontact.owl#operatingDataProperty"}]},{"@id":"http://ontology.eil.utoronto.ca/icontact.owl#hasOperatingHours","@type":["http://www.w3.org/2002/07/owl#ObjectProperty"],"http://www.w3.org/2000/01/rdf-schema#label":[{"@language":"en","@value":"has Operating Hours"}],"http://www.w3.org/2000/01/rdf-schema#range":[{"@id":"http://ontology.eil.utoronto.ca/icontact.owl#HoursOfOperation"}],"http://www.w3.org/2000/01/rdf-schema#subPropertyOf":[{"@id":"http://ontology.eil.utoronto.ca/icontact.owl#OperatingProperty"}]},{"@id":"http://ontology.eil.utoronto.ca/icontact.owl#hasPersonalEmail","@type":["http://www.w3.org/2002/07/owl#DatatypeProperty"],"http://www.w3.org/2000/01/rdf-schema#label":[{"@language":"en","@value":"has Personal Email"}],"http://www.w3.org/2000/01/rdf-schema#subPropertyOf":[{"@id":"http://ontology.eil.utoronto.ca/icontact.owl#emailDataProperty"}]},{"@id":"http://ontology.eil.utoronto.ca/icontact.owl#hasPhoneNumber","@type":["http://www.w3.org/2002/07/owl#DatatypeProperty"],"http://www.w3.org/2000/01/rdf-schema#label":[{"@language":"en","@value":"has Phone Number"}],"http://www.w3.org/2000/01/rdf-schema#subPropertyOf":[{"@id":"http://ontology.eil.utoronto.ca/icontact.owl#telephoneDataProperty"}]},{"@id":"http://ontology.eil.utoronto.ca/icontact.owl#hasPhoneType","@type":["http://www.w3.org/2002/07/owl#ObjectProperty"],"http://www.w3.org/2000/01/rdf-schema#label":[{"@language":"en","@value":"has Phone Type"}],"http://www.w3.org/2000/01/rdf-schema#range":[{"@id":"http://ontology.eil.utoronto.ca/icontact.owl#PhoneType"}],"http://www.w3.org/2000/01/rdf-schema#subPropertyOf":[{"@id":"http://ontology.eil.utoronto.ca/icontact.owl#contactProperty"}]},{"@id":"http://ontology.eil.utoronto.ca/icontact.owl#hasPostalCode","@type":["http://www.w3.org/2002/07/owl#DatatypeProperty"],"http://www.w3.org/2000/01/rdf-schema#label":[{"@language":"en","@value":"has Postal Code"}],"http://www.w3.org/2000/01/rdf-schema#subPropertyOf":[{"@id":"http://ontology.eil.utoronto.ca/icontact.owl#addressDataProperty"}]},{"@id":"http://ontology.eil.utoronto.ca/icontact.owl#hasState","@type":["http://www.w3.org/2002/07/owl#ObjectProperty"],"http://www.w3.org/2000/01/rdf-schema#label":[{"@language":"en","@value":"has State"}],"http://www.w3.org/2000/01/rdf-schema#subPropertyOf":[{"@id":"http://ontology.eil.utoronto.ca/icontact.owl#addressProperty"}]},{"@id":"http://ontology.eil.utoronto.ca/icontact.owl#hasStreet","@type":["http://www.w3.org/2002/07/owl#DatatypeProperty"],"http://www.w3.org/2000/01/rdf-schema#label":[{"@language":"en","@value":"has Street"}],"http://www.w3.org/2000/01/rdf-schema#subPropertyOf":[{"@id":"http://ontology.eil.utoronto.ca/icontact.owl#addressDataProperty"}]},{"@id":"http://ontology.eil.utoronto.ca/icontact.owl#hasStreetDirection","@type":["http://www.w3.org/2002/07/owl#ObjectProperty"],"http://www.w3.org/2000/01/rdf-schema#domain":[{"@id":"http://ontology.eil.utoronto.ca/icontact.owl#Address"}],"http://www.w3.org/2000/01/rdf-schema#label":[{"@language":"en","@value":"has Street Direction"}],"http://www.w3.org/2000/01/rdf-schema#range":[{"@id":"http://ontology.eil.utoronto.ca/icontact.owl#StreetDirection"}],"http://www.w3.org/2000/01/rdf-schema#subPropertyOf":[{"@id":"http://ontology.eil.utoronto.ca/icontact.owl#addressProperty"}]},{"@id":"http://ontology.eil.utoronto.ca/icontact.owl#hasStreetNumber","@type":["http://www.w3.org/2002/07/owl#DatatypeProperty"],"http://www.w3.org/2000/01/rdf-schema#label":[{"@language":"en","@value":"has Street Number"}],"http://www.w3.org/2000/01/rdf-schema#subPropertyOf":[{"@id":"http://ontology.eil.utoronto.ca/icontact.owl#addressDataProperty"}]},{"@id":"http://ontology.eil.utoronto.ca/icontact.owl#hasStreetType","@type":["http://www.w3.org/2002/07/owl#ObjectProperty"],"http://www.w3.org/2000/01/rdf-schema#domain":[{"@id":"http://ontology.eil.utoronto.ca/icontact.owl#Address"}],"http://www.w3.org/2000/01/rdf-schema#label":[{"@language":"en","@value":"has Street Type"}],"http://www.w3.org/2000/01/rdf-schema#range":[{"@id":"http://ontology.eil.utoronto.ca/icontact.owl#StreetType"}],"http://www.w3.org/2000/01/rdf-schema#subPropertyOf":[{"@id":"http://ontology.eil.utoronto.ca/icontact.owl#addressProperty"}]},{"@id":"http://ontology.eil.utoronto.ca/icontact.owl#hasTelephone","@type":["http://www.w3.org/2002/07/owl#ObjectProperty"],"http://www.w3.org/2000/01/rdf-schema#label":[{"@language":"en","@value":"has Telephone"}],"http://www.w3.org/2000/01/rdf-schema#subPropertyOf":[{"@id":"http://ontology.eil.utoronto.ca/icontact.owl#contactProperty"}]},{"@id":"http://ontology.eil.utoronto.ca/icontact.owl#hasUnitNumber","@type":["http://www.w3.org/2002/07/owl#DatatypeProperty"],"http://www.w3.org/2000/01/rdf-schema#label":[{"@language":"en","@value":"has Unit Number"}],"http://www.w3.org/2000/01/rdf-schema#subPropertyOf":[{"@id":"http://ontology.eil.utoronto.ca/icontact.owl#addressDataProperty"}]},{"@id":"http://ontology.eil.utoronto.ca/icontact.owl#hasWebSite","@type":["http://www.w3.org/2002/07/owl#DatatypeProperty"],"http://www.w3.org/2000/01/rdf-schema#label":[{"@language":"en","@value":"has Web Site"}],"http://www.w3.org/2000/01/rdf-schema#range":[{"@id":"http://www.w3.org/2001/XMLSchema#string"}],"http://www.w3.org/2000/01/rdf-schema#subPropertyOf":[{"@id":"http://ontology.eil.utoronto.ca/icontact.owl#hasContactDataProperty"}]},{"@id":"http://ontology.eil.utoronto.ca/icontact.owl#hasWorkEmail","@type":["http://www.w3.org/2002/07/owl#DatatypeProperty"],"http://www.w3.org/2000/01/rdf-schema#label":[{"@language":"en","@value":"has Work Email"}],"http://www.w3.org/2000/01/rdf-schema#subPropertyOf":[{"@id":"http://ontology.eil.utoronto.ca/icontact.owl#emailDataProperty"}]},{"@id":"http://ontology.eil.utoronto.ca/icontact.owl#iContactThing","@type":["http://www.w3.org/2002/07/owl#Class"]},{"@id":"http://ontology.eil.utoronto.ca/icontact.owl#operatingDataProperty","@type":["http://www.w3.org/2002/07/owl#DatatypeProperty"],"http://www.w3.org/2000/01/rdf-schema#subPropertyOf":[{"@id":"http://ontology.eil.utoronto.ca/icontact.owl#hasContactDataProperty"}]},{"@id":"http://ontology.eil.utoronto.ca/icontact.owl#telephoneDataProperty","@type":["http://www.w3.org/2002/07/owl#DatatypeProperty"],"http://www.w3.org/2000/01/rdf-schema#subPropertyOf":[{"@id":"http://ontology.eil.utoronto.ca/icontact.owl#hasContactDataProperty"}]},{"@id":"http://purl.org/dc/elements/1.1/creator","@type":["http://www.w3.org/2002/07/owl#AnnotationProperty"]},{"@id":"http://purl.org/dc/elements/1.1/date","@type":["http://www.w3.org/2002/07/owl#AnnotationProperty"]},{"@id":"http://purl.org/dc/elements/1.1/description","@type":["http://www.w3.org/2002/07/owl#AnnotationProperty"]},{"@id":"http://purl.org/dc/elements/1.1/issued","@type":["http://www.w3.org/2002/07/owl#AnnotationProperty"]},{"@id":"http://purl.org/dc/elements/1.1/title","@type":["http://www.w3.org/2002/07/owl#AnnotationProperty"]},{"@id":"http://purl.org/dc/terms/created","@type":["http://www.w3.org/2002/07/owl#AnnotationProperty"]},{"@id":"http://purl.org/dc/terms/creator","@type":["http://www.w3.org/2002/07/owl#AnnotationProperty"]},{"@id":"http://purl.org/dc/terms/description","@type":["http://www.w3.org/2002/07/owl#AnnotationProperty"]},{"@id":"http://purl.org/dc/terms/issued","@type":["http://www.w3.org/2002/07/owl#AnnotationProperty"]},{"@id":"http://purl.org/dc/terms/license","@type":["http://www.w3.org/2002/07/owl#AnnotationProperty"]},{"@id":"http://purl.org/dc/terms/modified","@type":["http://www.w3.org/2002/07/owl#AnnotationProperty"]},{"@id":"http://purl.org/dc/terms/rights","@type":["http://www.w3.org/2002/07/owl#AnnotationProperty"]},{"@id":"http://purl.org/dc/terms/title","@type":["http://www.w3.org/2002/07/owl#AnnotationProperty"]},{"@id":"http://purl.org/vocab/vann/preferredNamespacePrefix","@type":["http://www.w3.org/2002/07/owl#AnnotationProperty"]},{"@id":"http://purl.org/vocab/vann/preferredNamespaceUri","@type":["http://www.w3.org/2002/07/owl#AnnotationProperty"]},{"@id":"http://schema.org/City","@type":["http://www.w3.org/2002/07/owl#Class"],"http://www.w3.org/2000/01/rdf-schema#subClassOf":[{"@id":"http://ontology.eil.utoronto.ca/icontact.owl#SchemaOrgThing"}]},{"@id":"http://schema.org/Country","@type":["http://www.w3.org/2002/07/owl#Class"],"http://www.w3.org/2000/01/rdf-schema#subClassOf":[{"@id":"http://ontology.eil.utoronto.ca/icontact.owl#SchemaOrgThing"}]},{"@id":"http://schema.org/GeoCoordinates","@type":["http://www.w3.org/2002/07/owl#Class"],"http://www.w3.org/2000/01/rdf-schema#subClassOf":[{"@id":"http://ontology.eil.utoronto.ca/icontact.owl#SchemaOrgThing"}]},{"@id":"http://schema.org/State","@type":["http://www.w3.org/2002/07/owl#Class"],"http://www.w3.org/2000/01/rdf-schema#subClassOf":[{"@id":"http://ontology.eil.utoronto.ca/icontact.owl#SchemaOrgThing"}]},{"@id":"http://schema.org/domainIncludes","@type":["http://www.w3.org/2002/07/owl#AnnotationProperty"]},{"@id":"http://schema.org/rangeIncludes","@type":["http://www.w3.org/2002/07/owl#AnnotationProperty"]},{"@id":"http://www.opengis.net/ont/geosparql#SpatialObject","http://www.w3.org/2000/01/rdf-schema#subClassOf":[{"@id":"https://w3id.org/icity/SpatialLoc/SpatialLocOntologyThing"}]},{"@id":"http://www.opengis.net/ont/geosparql#asGML","http://www.w3.org/2000/01/rdf-schema#subPropertyOf":[{"@id":"https://w3id.org/icity/SpatialLoc/SpatialLocOntologyDataProperty"}]},{"@id":"http://www.opengis.net/ont/geosparql#asWKT","http://www.w3.org/2000/01/rdf-schema#subPropertyOf":[{"@id":"https://w3id.org/icity/SpatialLoc/SpatialLocOntologyDataProperty"}]},{"@id":"http://www.opengis.net/ont/geosparql#coordinateDimension","http://www.w3.org/2000/01/rdf-schema#subPropertyOf":[{"@id":"https://w3id.org/icity/SpatialLoc/SpatialLocOntologyDataProperty"}]},{"@id":"http://www.opengis.net/ont/geosparql#dimension","http://www.w3.org/2000/01/rdf-schema#subPropertyOf":[{"@id":"https://w3id.org/icity/SpatialLoc/SpatialLocOntologyDataProperty"}]},{"@id":"http://www.opengis.net/ont/geosparql#ehContains","http://www.w3.org/2000/01/rdf-schema#subPropertyOf":[{"@id":"https://w3id.org/icity/SpatialLoc/SpatialLocOntologyProperty"}]},{"@id":"http://www.opengis.net/ont/geosparql#ehCoveredBy","http://www.w3.org/2000/01/rdf-schema#subPropertyOf":[{"@id":"https://w3id.org/icity/SpatialLoc/SpatialLocOntologyProperty"}]},{"@id":"http://www.opengis.net/ont/geosparql#ehCovers","http://www.w3.org/2000/01/rdf-schema#subPropertyOf":[{"@id":"https://w3id.org/icity/SpatialLoc/SpatialLocOntologyProperty"}]},{"@id":"http://www.opengis.net/ont/geosparql#ehDisjoint","http://www.w3.org/2000/01/rdf-schema#subPropertyOf":[{"@id":"https://w3id.org/icity/SpatialLoc/SpatialLocOntologyProperty"}]},{"@id":"http://www.opengis.net/ont/geosparql#ehEquals","http://www.w3.org/2000/01/rdf-schema#subPropertyOf":[{"@id":"https://w3id.org/icity/SpatialLoc/SpatialLocOntologyProperty"}]},{"@id":"http://www.opengis.net/ont/geosparql#ehInside","http://www.w3.org/2000/01/rdf-schema#subPropertyOf":[{"@id":"https://w3id.org/icity/SpatialLoc/SpatialLocOntologyProperty"}]},{"@id":"http://www.opengis.net/ont/geosparql#ehMeet","http://www.w3.org/2000/01/rdf-schema#subPropertyOf":[{"@id":"https://w3id.org/icity/SpatialLoc/SpatialLocOntologyProperty"}]},{"@id":"http://www.opengis.net/ont/geosparql#ehOverlap","http://www.w3.org/2000/01/rdf-schema#subPropertyOf":[{"@id":"https://w3id.org/icity/SpatialLoc/SpatialLocOntologyProperty"}]},{"@id":"http://www.opengis.net/ont/geosparql#hasGeometry","http://www.w3.org/2000/01/rdf-schema#subPropertyOf":[{"@id":"https://w3id.org/icity/SpatialLoc/SpatialLocOntologyProperty"}]},{"@id":"http://www.opengis.net/ont/geosparql#hasSerialization","http://www.w3.org/2000/01/rdf-schema#subPropertyOf":[{"@id":"https://w3id.org/icity/SpatialLoc/SpatialLocOntologyDataProperty"}]},{"@id":"http://www.opengis.net/ont/geosparql#isEmpty","http://www.w3.org/2000/01/rdf-schema#subPropertyOf":[{"@id":"https://w3id.org/icity/SpatialLoc/SpatialLocOntologyDataProperty"}]},{"@id":"http://www.opengis.net/ont/geosparql#isSimple","http://www.w3.org/2000/01/rdf-schema#subPropertyOf":[{"@id":"https://w3id.org/icity/SpatialLoc/SpatialLocOntologyDataProperty"}]},{"@id":"http://www.opengis.net/ont/geosparql#rcc8dc","http://www.w3.org/2000/01/rdf-schema#subPropertyOf":[{"@id":"https://w3id.org/icity/SpatialLoc/SpatialLocOntologyProperty"}]},{"@id":"http://www.opengis.net/ont/geosparql#rcc8ec","http://www.w3.org/2000/01/rdf-schema#subPropertyOf":[{"@id":"https://w3id.org/icity/SpatialLoc/SpatialLocOntologyProperty"}]},{"@id":"http://www.opengis.net/ont/geosparql#rcc8eq","http://www.w3.org/2000/01/rdf-schema#subPropertyOf":[{"@id":"https://w3id.org/icity/SpatialLoc/SpatialLocOntologyProperty"}]},{"@id":"http://www.opengis.net/ont/geosparql#rcc8ntpp","http://www.w3.org/2000/01/rdf-schema#subPropertyOf":[{"@id":"https://w3id.org/icity/SpatialLoc/SpatialLocOntologyProperty"}]},{"@id":"http://www.opengis.net/ont/geosparql#rcc8ntppi","http://www.w3.org/2000/01/rdf-schema#subPropertyOf":[{"@id":"https://w3id.org/icity/SpatialLoc/SpatialLocOntologyProperty"}]},{"@id":"http://www.opengis.net/ont/geosparql#rcc8po","http://www.w3.org/2000/01/rdf-schema#subPropertyOf":[{"@id":"https://w3id.org/icity/SpatialLoc/SpatialLocOntologyProperty"}]},{"@id":"http://www.opengis.net/ont/geosparql#rcc8tpp","http://www.w3.org/2000/01/rdf-schema#subPropertyOf":[{"@id":"https://w3id.org/icity/SpatialLoc/SpatialLocOntologyProperty"}]},{"@id":"http://www.opengis.net/ont/geosparql#rcc8tppi","http://www.w3.org/2000/01/rdf-schema#subPropertyOf":[{"@id":"https://w3id.org/icity/SpatialLoc/SpatialLocOntologyProperty"}]},{"@id":"http://www.opengis.net/ont/geosparql#sfContains","http://www.w3.org/2000/01/rdf-schema#subPropertyOf":[{"@id":"https://w3id.org/icity/SpatialLoc/SpatialLocOntologyProperty"}]},{"@id":"http://www.opengis.net/ont/geosparql#sfCrosses","http://www.w3.org/2000/01/rdf-schema#subPropertyOf":[{"@id":"https://w3id.org/icity/SpatialLoc/SpatialLocOntologyProperty"}]},{"@id":"http://www.opengis.net/ont/geosparql#sfDisjoint","http://www.w3.org/2000/01/rdf-schema#subPropertyOf":[{"@id":"https://w3id.org/icity/SpatialLoc/SpatialLocOntologyProperty"}]},{"@id":"http://www.opengis.net/ont/geosparql#sfEquals","http://www.w3.org/2000/01/rdf-schema#subPropertyOf":[{"@id":"https://w3id.org/icity/SpatialLoc/SpatialLocOntologyProperty"}]},{"@id":"http://www.opengis.net/ont/geosparql#sfIntersects","http://www.w3.org/2000/01/rdf-schema#subPropertyOf":[{"@id":"https://w3id.org/icity/SpatialLoc/SpatialLocOntologyProperty"}]},{"@id":"http://www.opengis.net/ont/geosparql#sfOverlaps","http://www.w3.org/2000/01/rdf-schema#subPropertyOf":[{"@id":"https://w3id.org/icity/SpatialLoc/SpatialLocOntologyProperty"}]},{"@id":"http://www.opengis.net/ont/geosparql#sfTouches","http://www.w3.org/2000/01/rdf-schema#subPropertyOf":[{"@id":"https://w3id.org/icity/SpatialLoc/SpatialLocOntologyProperty"}]},{"@id":"http://www.opengis.net/ont/geosparql#sfWithin","http://www.w3.org/2000/01/rdf-schema#subPropertyOf":[{"@id":"https://w3id.org/icity/SpatialLoc/SpatialLocOntologyProperty"}]},{"@id":"http://www.opengis.net/ont/geosparql#spatialDimension","http://www.w3.org/2000/01/rdf-schema#subPropertyOf":[{"@id":"https://w3id.org/icity/SpatialLoc/SpatialLocOntologyDataProperty"}]},{"@id":"http://www.w3.org/1999/02/22-rdf-syntax-ns#List","http://www.w3.org/2000/01/rdf-schema#subClassOf":[{"@id":"https://w3id.org/icity/SpatialLoc/SpatialLocOntologyThing"}]},{"@id":"http://www.w3.org/2001/XMLSchema#date","@type":["http://www.w3.org/2000/01/rdf-schema#Datatype"]},{"@id":"http://www.w3.org/2001/XMLSchema#duration","@type":["http://www.w3.org/2000/01/rdf-schema#Datatype"]},{"@id":"http://www.w3.org/2001/XMLSchema#gDay","@type":["http://www.w3.org/2000/01/rdf-schema#Datatype"]},{"@id":"http://www.w3.org/2001/XMLSchema#gMonth","@type":["http://www.w3.org/2000/01/rdf-schema#Datatype"]},{"@id":"http://www.w3.org/2001/XMLSchema#gYear","@type":["http://www.w3.org/2000/01/rdf-schema#Datatype"]},{"@id":"http://www.w3.org/2001/XMLSchema#gYearMonth","@type":["http://www.w3.org/2000/01/rdf-schema#Datatype"]},{"@id":"http://www.w3.org/2001/XMLSchema#pattern","@type":["http://www.w3.org/2002/07/owl#AnnotationProperty"]},{"@id":"http://www.w3.org/2002/07/owl#versionInfo","@type":["http://www.w3.org/2002/07/owl#AnnotationProperty"]},{"@id":"http://www.w3.org/2003/01/geo/wgs84_pos#lat","@type":["http://www.w3.org/2002/07/owl#DatatypeProperty"],"http://www.w3.org/2000/01/rdf-schema#label":[{"@language":"en","@value":"lattitude"}],"http://www.w3.org/2000/01/rdf-schema#range":[{"@id":"http://www.w3.org/2001/XMLSchema#string"}],"http://www.w3.org/2000/01/rdf-schema#subPropertyOf":[{"@id":"http://ontology.eil.utoronto.ca/icontact.owl#addressDataProperty"}]},{"@id":"http://www.w3.org/2003/01/geo/wgs84_pos#long","@type":["http://www.w3.org/2002/07/owl#DatatypeProperty"],"http://www.w3.org/2000/01/rdf-schema#label":[{"@language":"en","@value":"longitude"}],"http://www.w3.org/2000/01/rdf-schema#range":[{"@id":"http://www.w3.org/2001/XMLSchema#string"}],"http://www.w3.org/2000/01/rdf-schema#subPropertyOf":[{"@id":"http://ontology.eil.utoronto.ca/icontact.owl#addressDataProperty"}]},{"@id":"http://www.w3.org/2004/02/skos/core#Collection","http://www.w3.org/2000/01/rdf-schema#subClassOf":[{"@id":"https://w3id.org/icity/SpatialLoc/SpatialLocOntologyThing"}]},{"@id":"http://www.w3.org/2004/02/skos/core#Concept","http://www.w3.org/2000/01/rdf-schema#subClassOf":[{"@id":"https://w3id.org/icity/SpatialLoc/SpatialLocOntologyThing"}]},{"@id":"http://www.w3.org/2004/02/skos/core#ConceptScheme","http://www.w3.org/2000/01/rdf-schema#subClassOf":[{"@id":"https://w3id.org/icity/SpatialLoc/SpatialLocOntologyThing"}]},{"@id":"http://www.w3.org/2004/02/skos/core#changeNote","@type":["http://www.w3.org/2002/07/owl#AnnotationProperty"]},{"@id":"http://www.w3.org/2004/02/skos/core#definition","@type":["http://www.w3.org/2002/07/owl#AnnotationProperty"]},{"@id":"http://www.w3.org/2004/02/skos/core#editorialNote","@type":["http://www.w3.org/2002/07/owl#AnnotationProperty"]},{"@id":"http://www.w3.org/2004/02/skos/core#example","@type":["http://www.w3.org/2002/07/owl#AnnotationProperty"]},{"@id":"http://www.w3.org/2004/02/skos/core#hasTopConcept","http://www.w3.org/2000/01/rdf-schema#subPropertyOf":[{"@id":"https://w3id.org/icity/SpatialLoc/SpatialLocOntologyProperty"}]},{"@id":"http://www.w3.org/2004/02/skos/core#historyNote","@type":["http://www.w3.org/2002/07/owl#AnnotationProperty"]},{"@id":"http://www.w3.org/2004/02/skos/core#inScheme","http://www.w3.org/2000/01/rdf-schema#subPropertyOf":[{"@id":"https://w3id.org/icity/SpatialLoc/SpatialLocOntologyProperty"}]},{"@id":"http://www.w3.org/2004/02/skos/core#member","http://www.w3.org/2000/01/rdf-schema#subPropertyOf":[{"@id":"https://w3id.org/icity/SpatialLoc/SpatialLocOntologyProperty"}]},{"@id":"http://www.w3.org/2004/02/skos/core#memberList","http://www.w3.org/2000/01/rdf-schema#subPropertyOf":[{"@id":"https://w3id.org/icity/SpatialLoc/SpatialLocOntologyProperty"}]},{"@id":"http://www.w3.org/2004/02/skos/core#notation","http://www.w3.org/2000/01/rdf-schema#subPropertyOf":[{"@id":"https://w3id.org/icity/SpatialLoc/SpatialLocOntologyDataProperty"}]},{"@id":"http://www.w3.org/2004/02/skos/core#note","@type":["http://www.w3.org/2002/07/owl#AnnotationProperty"]},{"@id":"http://www.w3.org/2004/02/skos/core#prefLabel","@type":["http://www.w3.org/2002/07/owl#AnnotationProperty"]},{"@id":"http://www.w3.org/2004/02/skos/core#scopeNote","@type":["http://www.w3.org/2002/07/owl#AnnotationProperty"]},{"@id":"http://www.w3.org/2004/02/skos/core#semanticRelation","http://www.w3.org/2000/01/rdf-schema#subPropertyOf":[{"@id":"https://w3id.org/icity/SpatialLoc/SpatialLocOntologyProperty"}]},{"@id":"http://www.w3.org/ns/adms#relatedDocumentation","@type":["http://www.w3.org/2002/07/owl#AnnotationProperty"]},{"@id":"http://xmlns.com/foaf/0.1/name","@type":["http://www.w3.org/2002/07/owl#AnnotationProperty"]},{"@id":"https://w3id.org/icity/SpatialLoc/SpatialLocOntologyDataProperty","@type":["http://www.w3.org/2002/07/owl#DatatypeProperty"],"http://www.w3.org/2000/01/rdf-schema#comment":[{"@value":"Created for organizational purposes, to identify data properties imported from geoSPARQL."}]},{"@id":"https://w3id.org/icity/SpatialLoc/SpatialLocOntologyProperty","@type":["http://www.w3.org/2002/07/owl#ObjectProperty"],"http://www.w3.org/2000/01/rdf-schema#comment":[{"@value":"Created for organizational purposes, to identify the object properties imported by geoSPARQL."}]},{"@id":"https://w3id.org/icity/SpatialLoc/SpatialLocOntologyThing","@type":["http://www.w3.org/2002/07/owl#Class"],"http://www.w3.org/2000/01/rdf-schema#comment":[{"@value":"Created for organizational purposes, to identify the classes imported from geoSPARQL."}]},{"@id":"https://w3id.org/icity/SpatialLoc/hasLocation","@type":["http://www.w3.org/2002/07/owl#ObjectProperty"],"http://www.w3.org/2000/01/rdf-schema#comment":[{"@value":"A property intended to relate non-spatial objects (e.g. activities) to a location(s) in space."}],"http://www.w3.org/2000/01/rdf-schema#range":[{"@id":"http://www.opengis.net/ont/geosparql#Feature"}],"http://www.w3.org/2000/01/rdf-schema#subPropertyOf":[{"@id":"https://w3id.org/icity/SpatialLoc/SpatialLocOntologyProperty"}]},{"@id":"https://w3id.org/icity/iContact/","@type":["http://www.w3.org/2002/07/owl#Ontology"],"http://purl.org/dc/elements/1.1/creator":[{"@value":"Mark Fox"},{"@value":"Megan Katsumi"}],"http://purl.org/dc/elements/1.1/description":[{"@value":"Ontology to capture concepts related to contact information (addresses, phone numbers). Reuses the iContact Ontology."}],"http://purl.org/dc/terms/created":[{"@type":"http://www.w3.org/2001/XMLSchema#date","@value":"2018-07-06"}],"http://purl.org/dc/terms/title":[{"@language":"en","@value":"iContact Ontology"}],"http://purl.org/vocab/vann/preferredNamespacePrefix":[{"@value":"icontact"}],"http://purl.org/vocab/vann/preferredNamespaceUri":[{"@value":"https://w3id.org/icity/iContact/"}],"http://www.w3.org/2000/01/rdf-schema#comment":[{"@value":"Developed as part of the overall iCity ontology effort.\n\t\tReuses the iContact ontology.\n\t\tCopyright @ 2016 Megan Katsumi, iCity Research Group\n\nChanges from previous version:\n"}],"http://www.w3.org/2002/07/owl#imports":[{"@id":"http://ontology.eil.utoronto.ca/icontact.owl"},{"@id":"https://w3id.org/icity/SpatialLoc/1.2/"}],"http://www.w3.org/2002/07/owl#versionIRI":[{"@id":"https://w3id.org/icity/iContact/1.0/"}],"http://www.w3.org/2002/07/owl#versionInfo":[{"@language":"en","@value":" Updated version of the iContact ontology, extended to include spatial feature. "}]}]